LICENSE.txt
MANIFEST.in
README.md
requirements.txt
setup.py
Bluto/__init__.py
Bluto/bluto
Bluto/email_data_test.py
Bluto/temp_testing_dict.py
Bluto/testing-badiu-search.py
Bluto/testing-dict-merge.py
Bluto.egg-info/PKG-INFO
Bluto.egg-info/SOURCES.txt
Bluto.egg-info/dependency_links.txt
Bluto.egg-info/requires.txt
Bluto.egg-info/top_level.txt
Bluto/doc/Subdomains-Raw.txt
Bluto/doc/countries.txt
Bluto/doc/sub_interest.txt
Bluto/doc/user_agents.txt
Bluto/modules/__init__.py
Bluto/modules/_wildSanitise.py
Bluto/modules/bluto_logging.py
Bluto/modules/data_mine.py
Bluto/modules/descriptor_.py
Bluto/modules/email_.py
Bluto/modules/execute.py
Bluto/modules/general.py
Bluto/modules/get_dnsNOTUSED.py
Bluto/modules/get_file.py
Bluto/modules/google-selen.py
Bluto/modules/html_report.py
Bluto/modules/in_out.py
Bluto/modules/logger_.py
Bluto/modules/output.py
Bluto/modules/update.py
Bluto/modules/use_age.py
Bluto/modules/b_classes/__init__.py
Bluto/modules/b_classes/class_calls.py
Bluto/modules/b_classes/linkedin_class.py
Bluto/modules/b_classes/thread_class.py