Metadata-Version: 2.1
Name: Bluto
Version: 3.0.18b0
Summary: 
Home-page: https://github.com/darryllane/Bluto
Author: Darryl lane
Author-email: DarrylLane101@gmail.com
License: LICENSE.txt
Platform: UNKNOWN
